{
  "collapse-filter": false,
  "search": "elastic network",
  "showTags": false,
  "showAttachments": false,
  "hideUnresolved": false,
  "showOrphans": true,
  "collapse-color-groups": true,
  "colorGroups": [],
  "collapse-display": true,
  "showArrow": false,
  "textFadeMultiplier": -2.1,
  "nodeSizeMultiplier": 1.12083333333333,
  "lineSizeMultiplier": 1.171875,
  "collapse-forces": false,
  "centerStrength": 0,
  "repelStrength": 0,
  "linkStrength": 1,
  "linkDistance": 500,
  "scale": 0.5357541709934611,
  "close": true
}